{
  "host": "localhost",
  "port": 3030,
  "public": "../public/",
  "paginate": {
    "default": 10,
    "max": 50
  },
  "authentication": {
    "entity": "user",
    "service": "users",
    "secret": "y2hgQNf+K/iM3H5rOyDS9ZjmtXQ=",
    "authStrategies": [
      "jwt",
      "local"
    ],
    "jwtOptions": {
      "header": {
        "typ": "access"
      },
      "audience": "https://yourdomain.com",
      "issuer": "feathers",
      "algorithm": "HS256",
      "expiresIn": "1d"
    },
    "local": {
      "usernameField": "email",
      "passwordField": "password"
    }
  },
  "mssql": {
    "client": "mssql",
    "connection": "mssql://sa:S@Tsql@dmin1@10.30.1.17/Kors"
  }
}
